embarrassingly/__init__.py
embarrassingly/conforming.py
embarrassingly/fastidious.py
embarrassingly/memorable.py
embarrassingly/parallel.py
embarrassingly/scatterbrained.py
embarrassingly/shy.py
embarrassingly/underpromoted.py
embarrassingly-0.0.6.dist-info/METADATA
embarrassingly-0.0.6.dist-info/WHEEL
embarrassingly-0.0.6.dist-info/entry_points.txt
embarrassingly-0.0.6.dist-info/top_level.txt
embarrassingly-0.0.6.dist-info/RECORD
