Metadata-Version: 2.1
Name: embarrassingly
Version: 0.0.6
Summary: Pimp your objective function for faster, robust optimization
Home-page: https://github.com/microprediction/embarrassingly
Author: microprediction
Author-email: pcotton@intechinvestments.com
License: MIT
Platform: UNKNOWN
Classifier: License :: OSI Approved :: MIT License
Classifier: Programming Language :: Python :: 3
Classifier: Programming Language :: Python :: 3.7
Requires-Dist: wheel
Requires-Dist: pathlib
Requires-Dist: numpy
Requires-Dist: scipy
Requires-Dist: scikit-learn
Requires-Dist: smt
Requires-Dist: tdigest
Requires-Dist: optuna
Requires-Dist: deap
Requires-Dist: microprediction
Requires-Dist: pandas
